<?xml version="1.0" encoding="UTF-8"?>
<actions>
        <action>
            <actionName>CUSTOM-deploy:deploy -e</actionName>
            <displayName>deploy:deploy -e</displayName>
            <goals>
                <goal>deploy:deploy</goal>
                <goal>-e</goal>
            </goals>
        </action>
        <action>
            <actionName>CUSTOM-glassfish:deploy</actionName>
            <displayName>glassfish:deploy</displayName>
            <goals>
                <goal>glassfish:deploy</goal>
            </goals>
        </action>
        <action>
            <actionName>CUSTOM-glassfish:deploy -e</actionName>
            <displayName>glassfish:deploy -e</displayName>
            <goals>
                <goal>glassfish:deploy</goal>
                <goal>-e</goal>
            </goals>
        </action>
        <action>
            <actionName>CUSTOM-glassfish:redeploy -e</actionName>
            <displayName>glassfish:redeploy -e</displayName>
            <goals>
                <goal>glassfish:redeploy</goal>
                <goal>-e</goal>
            </goals>
        </action>
        <action>
            <actionName>CUSTOM-glassfish:redeploy -e --debug</actionName>
            <displayName>glassfish:redeploy -e --debug</displayName>
            <goals>
                <goal>glassfish:deploy</goal>
                <goal>-e</goal>
                <goal>--debug</goal>
            </goals>
        </action>
        <action>
            <actionName>CUSTOM-properties:read-project-properties glassfish:deploy -e --debug</actionName>
            <displayName>properties:read-project-properties glassfish:deploy -e --debug</displayName>
            <goals>
                <goal>properties:read-project-properties</goal>
                <goal>glassfish:deploy</goal>
                <goal>-e</goal>
                <goal>--debug</goal>
            </goals>
        </action>
        <action>
            <actionName>CUSTOM-properties:read-project-properties glassfish:redeploy -e --debug</actionName>
            <displayName>properties:read-project-properties glassfish:redeploy -e --debug</displayName>
            <goals>
                <goal>properties:read-project-properties</goal>
                <goal>glassfish:redeploy</goal>
                <goal>-e</goal>
                <goal>--debug</goal>
            </goals>
        </action>
    </actions>
